setup.py
chaoslib/__init__.py
chaoslib.egg-info/PKG-INFO
chaoslib.egg-info/SOURCES.txt
chaoslib.egg-info/dependency_links.txt
chaoslib.egg-info/not-zip-safe
chaoslib.egg-info/requires.txt
chaoslib.egg-info/top_level.txt