Metadata-Version: 1.1
Name: chaoslib
Version: 0.0.1-Alpha
Summary: Sorting library for chaotic sorting.
Home-page: https://github.com/dansun/chaoslib
Author: Daniel Sundberg
Author-email: daniel@danielsundberg.nu
License: GNU v2
Download-URL: https://github.com/dansun/chaoslib
Platform: UNKNOWN
Classifier: Programming Language :: Python
Classifier: Programming Language :: Python :: 3
Classifier: Development Status :: 4 - Beta
Classifier: Intended Audience :: Developers
Classifier: License :: OSI Approved :: GNU General Public License v2 or later (GPLv2+)
Classifier: Operating System :: OS Independent
Classifier: Topic :: Software Development :: Libraries :: Python Modules
